[{"place_id": 127614101, "licence": "Data \u00a9 OpenStreetMap contributors, ODbL 1.0. http://osm.org/copyright", "osm_type": "way", "osm_id": 93091586, "lat": "50.8846081", "lon": "8.5449693", "class": "highway", "type": "residential", "place_rank": 26, "importance": 0.05338803921568624, "addresstype": "road", "name": "Wiesenstra\u00dfe", "display_name": "Wiesenstra\u00dfe, Eckelshausen, Biedenkopf, Landkreis Marburg-Biedenkopf, Hesse, 35216, Germany", "boundingbox": ["50.8840928", "50.8851515", "8.5448137", "8.5450456"]}]