[{"place_id": 127118757, "licence": "Data \u00a9 OpenStreetMap contributors, ODbL 1.0. http://osm.org/copyright", "osm_type": "way", "osm_id": 31536539, "lat": "50.8148952", "lon": "8.5294803", "class": "highway", "type": "residential", "place_rank": 26, "importance": 0.05338281147478443, "addresstype": "road", "name": "Steilweg", "display_name": "Steilweg, Holzhausen, Dautphetal, Landkreis Marburg-Biedenkopf, Hesse, 35232, Germany", "boundingbox": ["50.8147917", "50.8159703", "8.5274590", "8.5311209"]}]